MANIFEST.in
README.txt
setup.py
docs/HISTORY.txt
docs/LICENSE.txt
src/silva/__init__.py
src/silva.app.subscriptions.egg-info/PKG-INFO
src/silva.app.subscriptions.egg-info/SOURCES.txt
src/silva.app.subscriptions.egg-info/dependency_links.txt
src/silva.app.subscriptions.egg-info/namespace_packages.txt
src/silva.app.subscriptions.egg-info/not-zip-safe
src/silva.app.subscriptions.egg-info/requires.txt
src/silva.app.subscriptions.egg-info/top_level.txt
src/silva/app/__init__.py
src/silva/app/subscriptions/__init__.py
src/silva/app/subscriptions/configure.zcml
src/silva/app/subscriptions/errors.py
src/silva/app/subscriptions/ftesting.zcml
src/silva/app/subscriptions/interfaces.py
src/silva/app/subscriptions/service.png
src/silva/app/subscriptions/service.py
src/silva/app/subscriptions/smi.py
src/silva/app/subscriptions/subscribable.py
src/silva/app/subscriptions/testing.py
src/silva/app/subscriptions/views.py
src/silva/app/subscriptions/layout/already_subscribed_template.pt
src/silva/app/subscriptions/layout/cancellation_confirmation_template.pt
src/silva/app/subscriptions/layout/not_subscribed_template.pt
src/silva/app/subscriptions/layout/publication_event_template.pt
src/silva/app/subscriptions/layout/subscription_confirmation_template.pt
src/silva/app/subscriptions/smi_templates/subscriptionportlet.cpt
src/silva/app/subscriptions/static/subscribe.gif
src/silva/app/subscriptions/templates/confirmationpage.cpt
src/silva/app/subscriptions/tests/__init__.py
src/silva/app/subscriptions/tests/test_func_settings.py
src/silva/app/subscriptions/tests/test_manager.py
src/silva/app/subscriptions/tests/test_service.py
src/silva/app/subscriptions/tests/test_upgrader300.py
src/silva/app/subscriptions/upgrader/__init__.py
src/silva/app/subscriptions/upgrader/upgrade_300.py