Metadata-Version: 1.1
Name: silva.app.subscriptions
Version: 3.0.3
Summary: Let people subscribe to content changes in Silva CMS
Home-page: https://github.com/silvacms/silva.app.subscriptions
Author: Sylvain Viollon
Author-email: info@infrae.com
License: BSD
Keywords: silva app redirect permanent http
Platform: UNKNOWN
Classifier: Framework :: Zope2
Classifier: License :: OSI Approved :: BSD License
Classifier: Programming Language :: Python
Classifier: Topic :: Software Development :: Libraries :: Python Modules
